Ambra_Clone_eyork_rad/Clone.py
Ambra_Clone_eyork_rad/__init__.py
Ambra_Clone_eyork_rad/V2/account_configuration.py
Ambra_Clone_eyork_rad/V2/ambra_environment.py
Ambra_Clone_eyork_rad/V2/clone.py
ambra_clone_eyork_rad-0.0.3.dist-info/LICENSE
ambra_clone_eyork_rad-0.0.3.dist-info/METADATA
ambra_clone_eyork_rad-0.0.3.dist-info/WHEEL
ambra_clone_eyork_rad-0.0.3.dist-info/top_level.txt
ambra_clone_eyork_rad-0.0.3.dist-info/RECORD
